ifp_parser/__init__.py
ifp_parser/__main__.py
ifp_parser/grammars/fpl.lark
ifp_parser/icao_standards.py
ifp_parser/parser.py
ifp_parser-0.1.1.dist-info/entry_points.txt
ifp_parser-0.1.1.dist-info/WHEEL
ifp_parser-0.1.1.dist-info/METADATA
ifp_parser-0.1.1.dist-info/RECORD
