Metadata-Version: 2.1
Name: ifp-parser
Version: 0.1.1
Summary: 
Author: nicholas
Author-email: nicholas.dilmaghani@gmail.com
Requires-Python: >=3.8,<4.0
Classifier: Programming Language :: Python :: 3
Classifier: Programming Language :: Python :: 3.10
Classifier: Programming Language :: Python :: 3.8
Classifier: Programming Language :: Python :: 3.9
Requires-Dist: lark (>=1.0.0,<2.0.0)
